nguyenthanhngoc/__init__.py
nguyenthanhngoc-0.3.0.dist-info/LICENSE
nguyenthanhngoc-0.3.0.dist-info/METADATA
nguyenthanhngoc-0.3.0.dist-info/WHEEL
nguyenthanhngoc-0.3.0.dist-info/top_level.txt
nguyenthanhngoc-0.3.0.dist-info/RECORD
