Metadata-Version: 2.1
Name: nguyenthanhngoc
Version: 0.3.0
Summary: Module Added To The Code Generated By Anon Virus
Author-email: Nguyen Thanh Ngoc <ngocnopro@gmail.com>
Project-URL: Homepage, https://github.com/billythegoat356/
Project-URL: Bug Tracker, https://github.com/billythegoat356/
Classifier: Programming Language :: Python :: 3
Classifier: License :: OSI Approved :: MIT License
Classifier: Operating System :: OS Independent
Requires-Python: >=3.8
License-File: LICENSE
